pdcommandline/__init__.py
pdcommandline/commandline.py
pdcommandline/commandvalue.py
pdcommandline/exceptions.py
pdcommandline/formatter.py
pdcommandline/input_event.py
pdcommandline/input_posix.py
pdcommandline/input_provider.py
pdcommandline/input_windows.py
pdcommandline/lifecycle.py
pdcommandline/logger.py
pdcommandline/loglevels.py
pdcommandline/progress.py
pdcommandline/sstr.py
pdcommandline/style.py
pdcommandline/stylesettings.py
pdcommandline/threads.py
pdcommandline/writer.py
pdcommandline-0.1.5.dist-info/LICENSE
pdcommandline-0.1.5.dist-info/METADATA
pdcommandline-0.1.5.dist-info/WHEEL
pdcommandline-0.1.5.dist-info/top_level.txt
pdcommandline-0.1.5.dist-info/RECORD
