Metadata-Version: 2.1
Name: pdcommandline
Version: 0.1.5
Summary: Library to build multithreaded command line applications
Home-page: https://gitlab.com/pdbuild/pdcommandline
Author: Julian Dessecker
License: UNKNOWN
Platform: UNKNOWN
Classifier: Programming Language :: Python :: 3
Classifier: License :: OSI Approved :: MIT License
Classifier: Operating System :: OS Independent
Requires-Python: >=3.8
License-File: LICENSE
